bridgeobjects/__init__.py
bridgeobjects/_create_pbn_string.py
bridgeobjects/_file_constants.py
bridgeobjects/_parse_lin_string.py
bridgeobjects/_parse_pbn_string.py
bridgeobjects/_parse_rbn_string.py
bridgeobjects/_version.py
bridgeobjects/auction.py
bridgeobjects/board.py
bridgeobjects/call.py
bridgeobjects/card.py
bridgeobjects/constants.py
bridgeobjects/contract.py
bridgeobjects/denomination.py
bridgeobjects/event.py
bridgeobjects/file_operations.py
bridgeobjects/hand.py
bridgeobjects/suit.py
bridgeobjects/suit_base.py
bridgeobjects/trick.py
bridgeobjects-0.1.32.dist-info/WHEEL
bridgeobjects-0.1.32.dist-info/METADATA
bridgeobjects-0.1.32.dist-info/RECORD
