Metadata-Version: 2.3
Name: bridgeobjects
Version: 0.1.32
Summary: A collection of modules that allows the user to utilise objects used in bridge games, for example, a board or a contract.
Author: Jeff
Author-email: Jeff <<jeffwatkins2000@gmail.com>>
Requires-Python: ==3.13.*
